nfisis/__init__
nfisis/ensemble.py
nfisis/fuzzy.py
nfisis/genetic.py
nfisis-0.1.6.dist-info/METADATA
nfisis-0.1.6.dist-info/WHEEL
nfisis-0.1.6.dist-info/licenses/LICENSE
nfisis-0.1.6.dist-info/RECORD
