Metadata-Version: 2.4
Name: nfisis
Version: 0.1.6
Summary: New Fuzzy Inference Systems (NFISiS)
Project-URL: Homepage, https://github.com/kaikerochaalves/NFISiS_PyPi
Project-URL: Issues, https://github.com/kaikerochaalves/NFISiS_PyPi
Author-email: Kaike Sa Teles Rocha Alves <kaikerochaalves@outlook.com>
License-File: LICENSE
Classifier: License :: OSI Approved :: GNU General Public License v3 (GPLv3)
Classifier: Programming Language :: Python :: 3
Requires-Python: >=3.0
Requires-Dist: matplotlib
Requires-Dist: numpy
Requires-Dist: pandas
Requires-Dist: pygad
Requires-Dist: scikit-learn
Requires-Dist: scipy
Requires-Dist: tqdm
